nanogo_basecaller/__init__.py
nanogo_basecaller/cli.py
nanogo_basecaller/data_indexer.py
nanogo_basecaller/dorado_installer.py
nanogo_basecaller/core/__init__.py
nanogo_basecaller/core/command.py
nanogo_basecaller/core/environment.py
nanogo_basecaller/core/parallel.py
nanogo_basecaller/core/resource.py
nanogo_basecaller/core/slurm.py
nanogo_basecaller/core/tool.py
nanogo_basecaller/tools/__init__.py
nanogo_basecaller/tools/basecaller/__init__.py
nanogo_basecaller/tools/basecaller/custom.html.j2
nanogo_basecaller/tools/basecaller/dorado.py
nanogo_basecaller/tools/basecaller/samples_sheet.py
nanogo_basecaller/tools/versions/__init__.py
nanogo_basecaller/tools/versions/env_manager.py
nanogo_basecaller/tools/versions/exceptions.py
nanogo_basecaller/tools/versions/tool_version_parser.py
nanogo_basecaller/tools/versions/version_checker.py
nanogo_basecaller/utils/__init__.py
nanogo_basecaller/utils/cli_select.py
nanogo_basecaller/utils/file_finder.py
nanogo_basecaller/utils/file_parser.py
nanogo_basecaller/utils/id_extraction.py
nanogo_basecaller/utils/io_selection.py
nanogo_basecaller/utils/path_translator.py
nanogo_basecaller/utils/paths.py
nanogo_basecaller/utils/sequencing/__init__.py
nanogo_basecaller/utils/sequencing/extractors.py
nanogo_basecaller/utils/sequencing/metadata.py
nanogo_basecaller/utils/sequencing/models.py
nanogo_basecaller/workflows/__init__.py
nanogo_basecaller/workflows/basecalling.py
nanogo_basecaller-0.1.7.dist-info/licenses/AUTHORS.md
nanogo_basecaller-0.1.7.dist-info/licenses/LICENSE
nanogo_basecaller-0.1.7.dist-info/METADATA
nanogo_basecaller-0.1.7.dist-info/WHEEL
nanogo_basecaller-0.1.7.dist-info/entry_points.txt
nanogo_basecaller-0.1.7.dist-info/top_level.txt
nanogo_basecaller-0.1.7.dist-info/RECORD
