Metadata-Version: 2.4
Name: nanogo-basecaller
Version: 0.1.7
Summary: A bioinformatics pipeline for basecalling ONT NGS Data.
Home-page: https://github.com/phac-nml/nanogo-basecaller
Author: Gurasis Osahan
Author-email: gurasis.osahan@phac-aspc.gc.ca
License: GPL-3.0-or-later
Project-URL: Source, https://github.com/phac-nml/nanogo-basecaller
Project-URL: Tracker, https://github.com/phac-nml/nanogo-basecaller/-/issues
Project-URL: Documentation, https://github.com/phac-nml/nanogo-basecaller/wiki
Project-URL: Publication, https://github.com/phac-nml/nanogo-basecaller#citation
Project-URL: Contact, https://github.com/phac-nml/nanogo-basecaller#contact
Keywords: nanopore sequencing ONT bioinformatics dorado basecalling NGS pipeline primer-trimming
Classifier: Development Status :: 3 - Alpha
Classifier: Intended Audience :: Developers
Classifier: Intended Audience :: Science/Research
Classifier: Intended Audience :: Healthcare Industry
Classifier: Topic :: Scientific/Engineering :: Bio-Informatics
Classifier: Topic :: Scientific/Engineering :: Medical Science Apps.
Classifier: Topic :: Scientific/Engineering :: Artificial Intelligence
Classifier: Topic :: Scientific/Engineering :: Image Processing
Classifier: Topic :: Software Development :: Libraries :: Python Modules
Classifier: Topic :: System :: Distributed Computing
Classifier: Operating System :: OS Independent
Classifier: Operating System :: POSIX :: Linux
Classifier: Natural Language :: English
Classifier: Environment :: GPU :: NVIDIA CUDA
Classifier: Environment :: Console
Classifier: Framework :: Pytest
Classifier: License :: OSI Approved :: GNU General Public License (GPL)
Classifier: Programming Language :: Python :: 3
Classifier: Programming Language :: Python :: 3.8
Classifier: Programming Language :: Python :: 3.9
Classifier: Programming Language :: Python :: 3.10
Requires-Python: <=3.11
License-File: LICENSE
License-File: AUTHORS.md
Requires-Dist: build>=1.2.2.post1
Requires-Dist: certifi>=2025.1.31
Requires-Dist: charset-normalizer>=3.4.1
Requires-Dist: exceptiongroup>=1.2.2
Requires-Dist: platformdirs>=4.3.6
Requires-Dist: packaging>=24.2
Requires-Dist: wheel>=0.45.1
Requires-Dist: poetry-core>=2.1.1
Requires-Dist: pyproject-hooks>=1.2.0
Requires-Dist: numpy<2.0.0,>=1.24.3
Requires-Dist: scipy>=1.15.2
Requires-Dist: pandas>=2.2.3
Requires-Dist: polars>=0.20.31
Requires-Dist: pyarrow>=14.0.2
Requires-Dist: h5py>=3.10.0
Requires-Dist: pillow>=11.1.0
Requires-Dist: matplotlib>=3.10.1
Requires-Dist: contourpy>=1.3.1
Requires-Dist: kiwisolver>=1.4.8
Requires-Dist: plotly>=4.1.0
Requires-Dist: tqdm>=4.67.1
Requires-Dist: bio>=1.7.1
Requires-Dist: biopython>=1.85
Requires-Dist: mygene>=3.2.2
Requires-Dist: biothings-client>=0.4.1
Requires-Dist: pycoQC>=2.5.2
Requires-Dist: gprofiler-official>=1.0.0
Requires-Dist: lib-pod5>=0.3.10
Requires-Dist: pod5==0.3.10
Requires-Dist: vbz-h5py-plugin>=1.0.1
Requires-Dist: cython>=3.0.12
Requires-Dist: psutil>=7.0.0
Requires-Dist: six>=1.17.0
Requires-Dist: et-xmlfile>=2.0.0
Requires-Dist: iso8601>=2.1.0
Requires-Dist: python-dateutil>=2.9.0.post0
Requires-Dist: pytz>=2025.1
Requires-Dist: tzdata>=2025.1
Requires-Dist: requests>=2.32.3
Requires-Dist: httpcore>=1.0.7
Requires-Dist: httpx>=0.28.1
Requires-Dist: urllib3>=2.3.0
Requires-Dist: idna>=3.10
Requires-Dist: oauthlib>=3.2.2
Requires-Dist: google-auth>=2.38.0
Requires-Dist: grpcio>=1.71.0
Requires-Dist: markdown>=3.7
Requires-Dist: jinja2>=3.1.6
Requires-Dist: pooch>=1.8.2
Requires-Dist: openpyxl>=3.1.5
Requires-Dist: protobuf<3.20,>=3.9.2
Requires-Dist: gputil>=1.4.0
Requires-Dist: sniffio>=1.3.1
Requires-Dist: alive-progress>=3.2.0
Requires-Dist: about-time>=4.2.1
Requires-Dist: h11>=0.14.0
Requires-Dist: more-itertools>=10.6.0
Requires-Dist: grapheme>=0.6.0
Requires-Dist: cycler>=0.12.1
Requires-Dist: typing-extensions>=4.12.2
Requires-Dist: ipython>=8.34.0
Requires-Dist: anyio>=4.9.0
Requires-Dist: narwhals>=1.31.0
Dynamic: author
Dynamic: author-email
Dynamic: classifier
Dynamic: description
Dynamic: description-content-type
Dynamic: home-page
Dynamic: keywords
Dynamic: license
Dynamic: license-file
Dynamic: project-url
Dynamic: requires-dist
Dynamic: requires-python
Dynamic: summary
